val.py
val/__init__.py
val/tp.py
val-0.6.dist-info/metadata.json
val-0.6.dist-info/WHEEL
val-0.6.dist-info/top_level.txt
val-0.6.dist-info/pbr.json
val-0.6.dist-info/RECORD
val-0.6.dist-info/DESCRIPTION.rst
val-0.6.dist-info/METADATA
