Metadata-Version: 1.1
Name: val
Version: 0.6
Summary: Python object validator
Home-page: http://github.com/thisfred/val
Author: Eric Casteleijn
Author-email: thisfred@gmail.com
License: BSD
Keywords: validation validators
Platform: UNKNOWN
Classifier: Development Status :: 5 - Production/Stable
Classifier: Intended Audience :: Developers
Classifier: Topic :: Software Development :: Libraries
Classifier: License :: OSI Approved :: BSD License
Classifier: Programming Language :: Python :: 2
Classifier: Programming Language :: Python :: 2.6
Classifier: Programming Language :: Python :: 2.7
Classifier: Programming Language :: Python :: 3
Classifier: Programming Language :: Python :: 3.3
Classifier: Programming Language :: Python :: 3.4
